README.md
setup.cfg
setup.py
automapping/__init__.py
automapping/automapper.py
automapping/helpers.py
automapping/mapper.py
automapping/mapper_steps.py
automapping/partial_mapper.py
automapping/updater.py
automapping.egg-info/PKG-INFO
automapping.egg-info/SOURCES.txt
automapping.egg-info/dependency_links.txt
automapping.egg-info/top_level.txt
automapping/abstractions/__init__.py
automapping/abstractions/imapper.py
automapping/abstractions/imapping_builder.py
automapping/abstractions/imapping_step.py
automapping/abstractions/itype_pattern_matching.py
automapping/abstractions/iupdater.py
automapping/exceptions/__init__.py
automapping/exceptions/invalid_mapping.py
automapping/exceptions/missing_attribute_exception.py
automapping/exceptions/missing_mapping_exception.py
tests_units/__init__.py
tests_units/automapper_test.py
tests_units/helpers_test.py
tests_units/mapper_basic_test.py
tests_units/mapper_nested_test.py
tests_units/fixtures/__init__.py
tests_units/fixtures/mapper_module_fixture.py