Metadata-Version: 2.1
Name: automapping
Version: 0.0.1
Summary: A utility library to map between dataclass
Home-page: https://github.com/GabrielCpp/automapping
Author: Gabriel
Author-email: gabcpp17@gmail.com
License: UNKNOWN
Download-URL: https://github.com/GabrielCpp/automapping/archive/v0.0.1.tar.gz
Platform: UNKNOWN
Classifier: Programming Language :: Python :: 3
Classifier: License :: OSI Approved :: MIT License
Classifier: Operating System :: OS Independent
Requires-Python: >=3.7
